curriculum_sneks/__init__.py
curriculum_sneks/compliments.py
curriculum_sneks/docstrings.py
curriculum_sneks/files.py
curriculum_sneks/records.py
curriculum_sneks/sneks.py
curriculum_sneks/tests.py
curriculum_sneks-1.0.1.dist-info/LICENSE
curriculum_sneks-1.0.1.dist-info/METADATA
curriculum_sneks-1.0.1.dist-info/WHEEL
curriculum_sneks-1.0.1.dist-info/top_level.txt
curriculum_sneks-1.0.1.dist-info/RECORD
