Metadata-Version: 2.1
Name: curriculum-sneks
Version: 1.0.1
Summary: Pedal Feedback Functions for the Sneks Curriculum
Home-page: https://pedal-edu.github.io/pedal
Author: acbart
Author-email: acbart@udel.edu
License: Creative Commons Attribution-Noncommercial-Share Alike license
Keywords: feedback education teaching program analysis tifa cait sandbox pedal grading grader grade
Platform: UNKNOWN
Classifier: Programming Language :: Python :: 3
Classifier: Intended Audience :: Education
Classifier: Topic :: Education
Requires-Python: >=3.6
